tencentcloud/__init__.py
tencentcloud/teo/__init__.py
tencentcloud/teo/v20220106/__init__.py
tencentcloud/teo/v20220106/errorcodes.py
tencentcloud/teo/v20220106/models.py
tencentcloud/teo/v20220106/teo_client.py
tencentcloud/teo/v20220106/teo_client_async.py
tencentcloud/teo/v20220901/__init__.py
tencentcloud/teo/v20220901/errorcodes.py
tencentcloud/teo/v20220901/models.py
tencentcloud/teo/v20220901/teo_client.py
tencentcloud/teo/v20220901/teo_client_async.py
tencentcloud_sdk_python_teo-3.1.29.dist-info/METADATA
tencentcloud_sdk_python_teo-3.1.29.dist-info/WHEEL
tencentcloud_sdk_python_teo-3.1.29.dist-info/top_level.txt
tencentcloud_sdk_python_teo-3.1.29.dist-info/RECORD
